{
  "project_info": {
    "project_number": "622522364541",
    "project_id": "safirisha-2021",
    "storage_bucket": "safirisha-2021.appspot.com"
  },
  "client": [
    {
      "client_info": {
        "mobilesdk_app_id": "1:622522364541:android:946707e0f63d91954df714",
        "android_client_info": {
          "package_name": "com.safirisha"
        }
      },
      "oauth_client": [
        {
          "client_id": "622522364541-rt0066t9ii7nde37dl3itklutrbdlfpn.apps.googleusercontent.com",
          "client_type": 3
        }
      ],
      "api_key": [
        {
          "current_key": "AIzaSyDYf599lQTUA-CXcnfINFuqKn0fnqe6xBI"
        }
      ],
      "services": {
        "appinvite_service": {
          "other_platform_oauth_client": [
            {
              "client_id": "622522364541-rt0066t9ii7nde37dl3itklutrbdlfpn.apps.googleusercontent.com",
              "client_type": 3
            }
          ]
        }
      }
    }
  ],
  "configuration_version": "1"
}